LICENSE
README.md
setup.cfg
setup.py
bin/python-noenv.sh
bin/python-stripped-env
lib/vsc/__init__.py
lib/vsc/install/__init__.py
lib/vsc/install/ci.py
lib/vsc/install/commontest.py
lib/vsc/install/headers.py
lib/vsc/install/methodinspector.py
lib/vsc/install/shared_setup.py
lib/vsc/install/testing.py
lib/vsc_install.egg-info/PKG-INFO
lib/vsc_install.egg-info/SOURCES.txt
lib/vsc_install.egg-info/dependency_links.txt
lib/vsc_install.egg-info/namespace_packages.txt
lib/vsc_install.egg-info/requires.txt
lib/vsc_install.egg-info/top_level.txt
test/testing.py