Metadata-Version: 2.1
Name: vsc-install
Version: 0.22.1
Summary: vsc-install provides shared setuptools functions and classes for python libraries developed by UGent's HPC group
Home-page: https://github.com/hpcugent/vsc-install
Download-URL: 
Author: Stijn De Weirdt;Andy Georges;Jens Timmerman
Author-email: stijn.deweirdt@ugent.be, andy.georges@ugent.be, jens.timmerman@ugent.be
Maintainer: Stijn De Weirdt;Andy Georges;Jens Timmerman
Maintainer-email: stijn.deweirdt@ugent.be, andy.georges@ugent.be, jens.timmerman@ugent.be
License: LGPLv2+
Classifier: License :: OSI Approved :: GNU Lesser General Public License v2 or later (LGPLv2+)
License-File: LICENSE
